{
  "required": true,
  "minVersion": "0.8",
  "package": "net.hydra.jojomod.mixin",
  "refmap": "${mod_id}.refmap.json",
  "compatibilityLevel": "JAVA_17",
  "mixins": [
    "EntityAndData",
    "PlayerEntity",
    "PlayerEntityServer",
    "StandUserEntity",
    "WorldTickServer",
    "ZLevel",
    "ZMob",
    "access.AccessAbstractArrow",
    "access.AccessAbstractFurnaceMenu",
    "access.AccessAreaOfEffectCloud",
    "access.AccessBoatItem",
    "access.AccessCreeper",
    "access.AccessEnderMan",
    "access.AccessFire",
    "access.AccessInventory",
    "access.AccessLivingEntity",
    "access.AccessMinecartItem",
    "access.AccessMinecartTNT",
    "access.AccessSmithingTemplateItem",
    "access.AccessTargetGoal",
    "access.AccessWalkAnimationState",
    "achtung.AchtungBushBlock",
    "achtung.AchtungChorusFlowerBlock",
    "achtung.AchtungChorusPlantBlock",
    "achtung.AchtungCropBlock",
    "achtung.AchtungItemEntity",
    "achtung.AchtungPortalShapeMixin",
    "achtung.AchtungProjectile",
    "barrage.DazeBlazeAttackGoal",
    "barrage.DazeCreeper",
    "barrage.DazeCreeperIgnite",
    "barrage.DazeCrossbowAtk",
    "barrage.DazeMob",
    "barrage.DazeProjectileAtk",
    "barrage.DazeWitch",
    "block_throw.ThrowBlockFaceContext",
    "block_throw.ThrowBoat",
    "cinderella.CinderellaCreeper",
    "cinderella.CinderellaVillager",
    "d4c.D4CBlockBehaviour",
    "d4c.D4CBlockStateBase",
    "d4c.D4CItem",
    "d4c.D4CItemStack",
    "d4c.D4CLookAtPlayerGoal",
    "d4c.D4CSensing",
    "d4c.D4CTargetGoal",
    "d4c.dworlds.ChunkGeneratorD4CMixin",
    "d4c.dworlds.D4CDimensionArgument",
    "d4c.dworlds.D4CStopLogger",
    "d4c.dworlds.RegistryMixin",
    "d4c.dworlds.ServerAccessorMixin",
    "data_and_structures.DatalessBlock",
    "data_and_structures.DataRandomSpreadStructurePlacement",
    "data_and_structures.DataStructureTemplatePool",
    "effects.bleed.BleedFoodData",
    "effects.hex.HexItem",
    "fates.FateCakeBlockMixin",
    "fates.FateEntityMixin",
    "fates.FateFoodDataMixin",
    "fates.FateLivingEntity",
    "fates.FatePlayerMixin",
    "fates.FatesMobEffectMixin",
    "gravity.GravityAbstractArrowMixin",
    "gravity.GravityAbstractHorseMixin",
    "gravity.GravityAbstractMinecart",
    "gravity.GravityAbstractSkeletonMixin",
    "gravity.GravityAreaEffectCloudMixin",
    "gravity.GravityBegGoalMixin",
    "gravity.GravityBoatMixin",
    "gravity.GravityCamelMixin",
    "gravity.GravityChickenMixin",
    "gravity.GravityCrossbowItemMixin",
    "gravity.GravityDirectionMixin",
    "gravity.GravityDrownedMixin",
    "gravity.GravityEndermanFreezeWhenLookedAtMixin",
    "gravity.GravityEnderManMixin",
    "gravity.GravityEntityCollisionContextMixin",
    "gravity.GravityEntityMixin",
    "gravity.GravityExperienceBottleItemMixin",
    "gravity.GravityExperienceOrbMixin",
    "gravity.GravityExplosionMixin",
    "gravity.GravityFallingBlockEntityMixin",
    "gravity.GravityFishingHookMixin",
    "gravity.GravityFoxMixin",
    "gravity.GravityGroundPathNavigationMixin",
    "gravity.GravityIllusionerMixin",
    "gravity.GravityItemEntityMixin",
    "gravity.GravityItemMixin",
    "gravity.GravityLivingEntityMixin",
    "gravity.GravityLlamaMixin",
    "gravity.GravityLlamaSpitMixin",
    "gravity.GravityLookAtPlayerGoalMixin",
    "gravity.GravityLookControlMixin",
    "gravity.GravityMeleeAttackGoalMixin",
    "gravity.GravityMobMixin",
    "gravity.GravityMoveControlMixin",
    "gravity.GravityPathMixin",
    "gravity.GravityPathNavigationMixin",
    "gravity.GravityPiglinMixin",
    "gravity.GravityPillagerMixin",
    "gravity.GravityPistonMovingBlockEntityMixin",
    "gravity.GravityPlayerListMixin",
    "gravity.GravityPlayerMixin",
    "gravity.GravityPointedDripstoneBlockMixin",
    "gravity.GravityPrimedTNTMixin",
    "gravity.GravityProjectileMixin",
    "gravity.GravityRamTargetMixin",
    "gravity.GravityServerGamePacketListenerImplMixin",
    "gravity.GravityShulkerBoxBlockEntityMixin",
    "gravity.GravityShulkerMixin",
    "gravity.GravitySnowGolemMixin",
    "gravity.GravityThrowablePotionItemMixin",
    "gravity.GravityThrowableProjectileMixin",
    "gravity.GravityThrownExperienceBottleMixin",
    "gravity.GravityThrownPotionMixin",
    "gravity.GravityUseOnContextMixin",
    "gravity.GravityWalkNodeEvaluatorMixin",
    "gravity.GravityWitchMixin",
    "gravity.GravityWitherBossMixin",
    "gravity.client.GravityClientEntityMixin",
    "gravity.fall_distance.GravityServerPlayerFall",
    "gravity.item.GravityBehaviorUtilsMixin",
    "green_day.ZProjectile",
    "items.AbilityCancelsEnderPearlItem",
    "items.BowlerHatItemInHandLayerMixin",
    "items.BowlerHatItemRendererMixin",
    "items.BowlerHatPlayerRendererMixin",
    "items.BowlerHatUnRenderHelmetMixin",
    "items.ExecutionerAxeRaid",
    "items.GasolineBucketBucketItem",
    "items.MaskItemEntity",
    "items.RaidItemEntity",
    "items.StandArrowBowItem",
    "items.StandCancelsShieldItem",
    "items.StereoRecordItem",
    "items.UnenchantAnvilMenu",
    "items.scissors.ScissorsBeehiveBlock",
    "items.scissors.ScissorsMushroomCow",
    "items.scissors.ScissorsPumpkinBlock",
    "items.scissors.ScissorsSheep",
    "items.scissors.ScissorsSnowGolem",
    "items.scissors.ScissorsTripWireBlock",
    "jojo_npcs.NPCVillagerZombieHostilesSensor",
    "jojo_npcs.NPCZombie",
    "jojo_npcs.NPCZombieVillager",
    "justice.JusticeCreeper",
    "justice.JusticeDamageSourceMixin",
    "justice.JusticeDefendVillageTargetGoal",
    "justice.JusticeFixScreenBugInventoryScreenMixin",
    "justice.JusticeIronGolem",
    "justice.JusticeItemEntity",
    "justice.JusticeNearestAttackableTargetGoal",
    "justice.JusticeRaider",
    "justice.JusticeTargetGoal",
    "justice.JusticeVillager",
    "justice.JusticeVillagerHostilesSensor",
    "justice.JusticeZombie",
    "magicians_red.MagiciansRedAbstractFurnaceBlockEntityMixin",
    "magicians_red.StandFirePortalShapeMixin",
    "networking.ZServerGamePacketListenerImpl",
    "piloting.PilotingServerGamePacketListenerImpl",
    "piloting.PilotingServerPlayerGameMode",
    "soft_and_wet.EncasementAbstractHorse",
    "soft_and_wet.SoftAndWetAllaySounds",
    "soft_and_wet.SoftAndWetBowItem",
    "soft_and_wet.SoftAndWetCalibratedSculkSensorBlockEntity",
    "soft_and_wet.SoftAndWetCreeper",
    "soft_and_wet.SoftAndWetNearestAttackableTargetGoal",
    "soft_and_wet.SoftAndWetPiglinAiMixin",
    "soft_and_wet.SoftAndWetPowderSnowBlock",
    "soft_and_wet.SoftAndWetSculkSensorBlockEntity",
    "soft_and_wet.SoftAndWetSculkShriekerBlockEntity",
    "soft_and_wet.SoftAndWetSonicBoom",
    "soft_and_wet.SoftAndWetTargetGoal",
    "soft_and_wet.SoftAndWetWardenSounds",
    "stand_entities.StandNearestAttackableTargetGoal",
    "stand_entities.StandWarden",
    "stand_entities.StandWitherBoss",
    "stand_entities.TeleportStandPassengers",
    "stand_users.PermaCastWorld",
    "stand_users.PowersBlock",
    "stand_users.PowersItemStack",
    "stand_users.PowersItemUsedOnLocationTrigger",
    "stand_users.UserAIAbstractSchoolingFish",
    "stand_users.UserAIPanicGoal",
    "stand_users.UserAIVillager",
    "stand_users.WorthyAnimal",
    "stand_users.WorthyVillagerMakeLove",
    "star_platinum.StarPlatinumAbstractArrow",
    "star_platinum.StarPlatinumExperienceOrb",
    "star_platinum.StarPlatinumItemEntity",
    "star_platinum.StarPlatinumTridentEntity",
    "survivor.SurvivorBrain",
    "survivor.SurvivorThrownPotion",
    "time_stop.TimeStopAbstractArrow",
    "time_stop.TimeStopBlockEntity",
    "time_stop.TimeStopBoatAccess",
    "time_stop.TimeStopBubbleColumn",
    "time_stop.TimeStopChestBlock",
    "time_stop.TimeStopFishingHook",
    "time_stop.TimeStopHangingEntityMixin",
    "time_stop.TimeStopItemEntity",
    "time_stop.TimeStopPrimedTnt",
    "time_stop.TimeStopProjectile",
    "time_stop.TimeStopRaid",
    "time_stop.TimeStopSlime",
    "time_stop.TimeStopThrowableProjectile",
    "time_stop.TimeStopWarden",
    "time_stop.TimeStopWorld",
    "vanilla_tweaks.ErrorFixUtil",
    "vanilla_tweaks.TameAbstractHorse"
  ],
  "client": [
    "HudRendering",
    "InputEvents",
    "PlayerEntityAbstractClient",
    "PlayerEntityClient",
    "SittingCameraMixin",
    "StandUserClientOnly",
    "WorldTickClient",
    "ZEntityRenderDispatcher",
    "ZItemInHandLayer",
    "ZItemInHandRenderer",
    "ZLevelRenderer",
    "ZLivingEntityRenderer",
    "ZMinecraftClient",
    "ZPlayerModel",
    "ZPlayerRender",
    "ZWorldRenderer",
    "access.AccessParticle",
    "access.AccessRenderSystem",
    "access.AccessViewArea",
    "achtung.AchtungArrowLayer",
    "achtung.AchtungArrowRenderer",
    "achtung.AchtungBannerRendererMixin",
    "achtung.AchtungCustomHeadLayer",
    "achtung.AchtungEntityRenderDispatcher",
    "achtung.AchtungEyesLayer",
    "achtung.AchtungGameRenderer",
    "achtung.AchtungHumanoidArmorLayer",
    "achtung.AchtungItemBlockRenderTypes",
    "achtung.AchtungItemInHandRenderer",
    "achtung.AchtungItemPickupParticle",
    "achtung.AchtungItemRenderer",
    "achtung.AchtungLevelRenderer",
    "achtung.AchtungModel",
    "achtung.AchtungModelPart",
    "animations.AnimationsElytraModel",
    "animations.AnimationsHumanoidModel",
    "barrage.BarrageBossBar",
    "barrage.DazeGameRenderer",
    "d4c.D4CDisableBlockInteraction",
    "fates.FatesLocalPlayerMixin",
    "gravity.client.GravityBiomeAmbientSoundsHandlerMixin",
    "gravity.client.GravityCameraMixin",
    "gravity.client.GravityClientPacketListener",
    "gravity.client.GravityClientPlayNetworkHandlerMixin",
    "gravity.client.GravityEntityRenderDispatcherMixin",
    "gravity.client.GravityEntityRendererMixin",
    "gravity.client.GravityGameRendererMixin",
    "gravity.client.GravityItemParticlePickupMixin",
    "gravity.client.GravityLocalPlayerMixin",
    "gravity.client.GravityPlayerRendererMixin",
    "gravity.client.GravityScreenEffectRenderer",
    "gui.ConfigOptionsScreen",
    "items.BowlerHatPlayerRendererMixin",
    "items.ChairCameraMixin",
    "items.StoneMaskCustomHeadLayerMixin",
    "items.visages.VisageHumanoidArmorLayer",
    "justice.JusticeAbstractZombieRenderer",
    "justice.JusticeFogRenderer",
    "justice.JusticeHumanoidArmorLayer",
    "justice.JusticeItemRenderer",
    "justice.JusticeMobRenderer",
    "justice.JusticeSkeletonRenderer",
    "keyboard.KeysKeyboardHandler",
    "keyboard.KeysKeyboardInput",
    "keyboard.KeysKeyMapping",
    "locacaca.StoneMultiplayerGamemode",
    "magicians_red.GeckolibCompatMixin",
    "magicians_red.MagiciansRedAbstractFurnaceScreenMixin",
    "magicians_red.StandFireScreenEffectRendererMixin",
    "model_layers.LayerHumanoidMobRendererMixin",
    "model_layers.LayerPlayerRendererMixin",
    "model_registry.CustomItemRendererMixin",
    "model_registry.RegisterBlockEntityWithoutLevelRenderer",
    "model_registry.RegisterItemRenderer",
    "model_registry.RegisterModelBakery",
    "model_registry.ZBlockModelShaper",
    "networking.ZClientGamePacketListener",
    "piloting.PilotingCamera",
    "piloting.PilotingGameRenderer",
    "piloting.PilotingMultiPlayerGameMode",
    "piloting.PilotingScreenEffectRenderer",
    "shaders.PostChainMixin",
    "shaders.ShaderGameRenderer",
    "soft_and_wet.SoftAndWetSoundManager",
    "stand_users.LoweringItemInHandRenderer",
    "stand_users.PowersMultiPlayerGameMode",
    "star_platinum.ScopeGameRenderer",
    "star_platinum.StarPlatinumLightTexture",
    "star_platinum.StarPlatinumMouseHandler",
    "time_stop.DayInterpolationClientLevelData",
    "time_stop.TimeStopBannerRenderer",
    "time_stop.TimeStopBlockEntityClient",
    "time_stop.TimeStopBlockEntityRenderDispatcher",
    "time_stop.TimeStopGameRenderer",
    "time_stop.TimeStopHumanoidArmorLayer",
    "time_stop.TimeStopItemInHandRenderer",
    "time_stop.TimeStopParticle",
    "time_stop.TimeStopParticleEngine",
    "time_stop.TimeStopTextureManager",
    "vanilla_tweaks.SBRHorseMarkingLayer",
    "vanilla_tweaks.SBRHorseRenderer",
    "vanilla_tweaks.VanillaGhostMobRenderer"
  ],
  "server": [
  ],
  "injectors": {
    "defaultRequire": 1
  }
}

